cdk_cloudformation_paloaltonetworks_cloudngfw_ngfw/__init__.py
cdk_cloudformation_paloaltonetworks_cloudngfw_ngfw/py.typed
cdk_cloudformation_paloaltonetworks_cloudngfw_ngfw/_jsii/__init__.py
cdk_cloudformation_paloaltonetworks_cloudngfw_ngfw/_jsii/paloaltonetworks-cloudngfw-ngfw@2.0.0-alpha.7.jsii.tgz
cdk_cloudformation_paloaltonetworks_cloudngfw_ngfw-2.0.0a7.dist-info/LICENSE
cdk_cloudformation_paloaltonetworks_cloudngfw_ngfw-2.0.0a7.dist-info/METADATA
cdk_cloudformation_paloaltonetworks_cloudngfw_ngfw-2.0.0a7.dist-info/WHEEL
cdk_cloudformation_paloaltonetworks_cloudngfw_ngfw-2.0.0a7.dist-info/top_level.txt
cdk_cloudformation_paloaltonetworks_cloudngfw_ngfw-2.0.0a7.dist-info/RECORD
